{
    "code": "http://www.iop.rwth-aachen.de/PPC/1/1/EnumAssetStatus",
    "preferred_name": "asset status",
    "synonymous_name": null,
    "short_name": "@STAS",
    "version_number": 1,
    "revision_number": 1,
    "Enumerated list of terms": "http://www.iop.rwth-aachen.de/PPC/1/1/construction\nhttp://www.iop.rwth-aachen.de/PPC/1/1/verification\nhttp://www.iop.rwth-aachen.de/PPC/1/1/approved\nhttp://www.iop.rwth-aachen.de/PPC/1/1/updating\nhttp://www.iop.rwth-aachen.de/PPC/1/1/expired",
    "Enumeration code list": "CONST\nVERY\nAPPR\nUPDT\nEXPI",
    "Applicable properties": "http://www.iop.rwth-aachen.de/PPC/1/1/status",
    "definition": null,
    "source_document_of_definition": null,
    "note": null,
    "remark": null,
    "definition_class": "http://www.iop.rwth-aachen.de/PPC/1/1/part\nhttp://www.iop.rwth-aachen.de/PPC/1/1/batch\nhttp://www.iop.rwth-aachen.de/PPC/1/1/billOfMaterial\nhttp://www.iop.rwth-aachen.de/PPC/1/1/BOMPosition",
    "status_level": "Proposal",
    "version_released_on": null,
    "revision_released_on": null,
    "obsolete_date": null,
    "version_initiated_on": null
}